scribe_python_client/__init__.py
scribe_python_client/cli.py
scribe_python_client/client.py
scribe_python_client/constants.py
scribe_python_client/lineage_graph.py
scribe_python_client/utils.py
scribe_python_client/version.py
scribe_python_client/yaml_export.py
scribe_python_client/mcp_app/__init__.py
scribe_python_client/mcp_app/app.py
scribe_python_client/mcp_app/endpointsAPI.py
scribe_python_client/mcp_app/main.py
scribe_python_client/mcp_app/query.json
scribe_python_client/mcp_app/responseAPi.py
scribe_python_client/mcp_app/testEndpoint.py
scribe_python_client/mcp_app/toolsDescriptions/updateToolDocs.py
scribe_python_client/mcp_app/toolsDescriptions/updatedToolDocs.json
scribe_python_client/mcp_app/toolsDescriptions/fullToolDocs/full_tool_docs.json
scribe_python_client/mcp_app/toolsDescriptions/fullToolDocs/functionDocumention.json
scribe_python_client/mcp_app/toolsDescriptions/fullToolDocs/queryDescription.json
scribe_python_client/mcp_app/toolsDescriptions/fullToolDocs/queryExamples.json
scribe_python_client/mcp_app/toolsDescriptions/fullToolDocs/queryParams.json
scribe_python_client/mcp_app/toolsDescriptions/fullToolDocs/queryTables.json
scribe_python_client-0.2.25.dist-info/licenses/LICENSE
scribe_python_client-0.2.25.dist-info/METADATA
scribe_python_client-0.2.25.dist-info/WHEEL
scribe_python_client-0.2.25.dist-info/entry_points.txt
scribe_python_client-0.2.25.dist-info/top_level.txt
scribe_python_client-0.2.25.dist-info/RECORD
