Metadata-Version: 2.4
Name: scribe-python-client
Version: 0.2.25
Summary: A Python client for interacting with ScribeHub.
Home-page: https://github.com/scribe-security/scribe-python-client
Author: Daniel Nebenzahl
Author-email: dn@scribesecurity.com
Classifier: Programming Language :: Python :: 3
Classifier: License :: OSI Approved :: MIT License
Classifier: Operating System :: OS Independent
Requires-Python: >=3.6
License-File: LICENSE
Requires-Dist: requests
Requires-Dist: PyJWT
Requires-Dist: python-dotenv
Provides-Extra: mcp
Requires-Dist: fastapi; extra == "mcp"
Requires-Dist: uvicorn; extra == "mcp"
Requires-Dist: fastapi_mcp; extra == "mcp"
Requires-Dist: python-dotenv; extra == "mcp"
Provides-Extra: graph
Requires-Dist: plotly; extra == "graph"
Requires-Dist: numpy; extra == "graph"
Requires-Dist: networkx; extra == "graph"
Requires-Dist: pyvis; extra == "graph"
Provides-Extra: all
Requires-Dist: fastapi; extra == "all"
Requires-Dist: uvicorn; extra == "all"
Requires-Dist: fastapi_mcp; extra == "all"
Requires-Dist: plotly; extra == "all"
Requires-Dist: numpy; extra == "all"
Requires-Dist: networkx; extra == "all"
Requires-Dist: pyvis; extra == "all"
Requires-Dist: python-dotenv; extra == "all"
Dynamic: author
Dynamic: author-email
Dynamic: classifier
Dynamic: description
Dynamic: description-content-type
Dynamic: home-page
Dynamic: license-file
Dynamic: provides-extra
Dynamic: requires-dist
Dynamic: requires-python
Dynamic: summary
